{"width":2177,"imagePath":"weilaishousidian_tex_0.png","name":"weilaishousidian","SubTexture":[{"width":2173,"y":700,"height":349,"name":"未来寿司店-3/天","x":2},{"width":101,"y":1980,"height":44,"name":"未来寿司店-3/中云","x":673},{"width":1279,"y":1642,"height":139,"name":"未来寿司店-3/后景","x":2},{"width":70,"y":1597,"height":32,"name":"未来寿司店-3/右云","x":1166},{"width":124,"y":1756,"height":52,"name":"未来寿司店-3/左云","x":1740},{"width":188,"y":1783,"height":164,"name":"未来寿司店-3/右后A","x":900},{"width":432,"y":1597,"height":146,"name":"未来寿司店-3/左后B","x":1283},{"width":83,"y":1830,"height":137,"name":"未来寿司店-3/中B","x":2086},{"width":154,"y":1949,"height":89,"name":"未来寿司店-3/左B","x":900},{"width":131,"y":1931,"height":115,"name":"未来寿司店-3/右B","x":1256},{"width":195,"y":1903,"height":115,"name":"未来寿司店-3/中A","x":1486},{"width":530,"y":1783,"height":186,"name":"未来寿司店-3/右A","x":2},{"width":219,"y":1654,"height":174,"name":"未来寿司店-3/左A","x":1895},{"width":95,"y":1931,"height":66,"name":"未来寿司店-3/飞碟B","x":1389},{"width":7,"y":1959,"height":8,"name":"未来寿司店-3/小怪触角右","x":1080},{"width":7,"y":1949,"height":8,"name":"未来寿司店-3/小怪触角左","x":1080},{"width":22,"y":1597,"height":24,"name":"未来寿司店-3/小怪身","x":1238},{"width":9,"y":1619,"height":9,"name":"未来寿司店-3/小怪眼","x":1262},{"width":80,"y":1999,"height":44,"name":"未来寿司店-3/飞碟A","x":1389},{"width":1162,"y":1051,"height":589,"name":"未来寿司店-3/中间光_右","x":2},{"width":252,"y":1317,"height":278,"name":"未来寿司店-3/jqr_身后","x":1166},{"width":235,"y":1051,"height":186,"name":"未来寿司店-3/jqr_脸","x":1937},{"width":97,"y":1631,"height":6,"name":"未来寿司店-3/jqr_眨眼","x":1166},{"width":98,"y":1980,"height":45,"name":"未来寿司店-3/jqr_眼","x":776},{"width":1920,"y":2,"height":696,"name":"桌面","x":2},{"width":105,"y":1259,"height":46,"name":"未来寿司店-3/右大臂后","x":1468},{"width":45,"y":1903,"height":29,"name":"未来寿司店-3/右大臂棍","x":1683},{"width":19,"y":1259,"height":20,"name":"未来寿司店-3/右大臂珠","x":1682},{"width":98,"y":1257,"height":51,"name":"未来寿司店-3/右大臂前","x":1704},{"width":44,"y":1257,"height":55,"name":"未来寿司店-3/右轴","x":1804},{"width":78,"y":1970,"height":74,"name":"未来寿司店-3/小臂右","x":1056},{"width":105,"y":1259,"height":46,"name":"未来寿司店-3/左大臂后","x":1575},{"width":45,"y":1934,"height":29,"name":"未来寿司店-3/左大臂棍","x":1683},{"width":19,"y":1597,"height":20,"name":"未来寿司店-3/左大臂珠","x":1262},{"width":98,"y":1970,"height":51,"name":"未来寿司店-3/左大臂前","x":1136},{"width":44,"y":1527,"height":55,"name":"未来寿司店-3/左轴","x":1660},{"width":78,"y":1969,"height":74,"name":"未来寿司店-3/小臂左","x":2086},{"width":252,"y":1756,"height":145,"name":"未来寿司店-3/jqr_身前","x":1486},{"width":176,"y":1527,"height":227,"name":"weilaishousidian_05","x":1717},{"frameY":-28,"y":1783,"frameWidth":176,"frameHeight":227,"width":164,"height":185,"name":"weilaishousidian_04","frameX":-6,"x":1090},{"frameY":-12,"y":1830,"frameWidth":176,"frameHeight":227,"width":168,"height":215,"name":"weilaishousidian_03","frameX":-4,"x":1916},{"frameY":-16,"y":1830,"frameWidth":176,"frameHeight":227,"width":174,"height":208,"name":"weilaishousidian_02","frameX":-1,"x":1740},{"frameY":-23,"y":1783,"frameWidth":176,"frameHeight":227,"width":170,"height":195,"name":"weilaishousidian_01","frameX":-3,"x":728},{"frameY":-11,"y":1960,"frameWidth":137,"frameHeight":94,"width":137,"height":82,"name":"weilaishousidian_11","frameX":0,"x":534},{"frameY":-28,"y":426,"frameWidth":300,"frameHeight":264,"width":240,"height":209,"name":"Smoke 09_00014","frameX":-30,"x":1924},{"frameY":-97,"y":637,"frameWidth":300,"frameHeight":264,"width":71,"height":60,"name":"Smoke 09_00002","frameX":-120,"x":1924},{"frameY":-28,"y":1317,"frameWidth":300,"frameHeight":264,"width":237,"height":208,"name":"Smoke 09_00012","frameX":-31,"x":1660},{"frameY":-27,"y":2,"frameWidth":300,"frameHeight":264,"width":240,"height":210,"name":"Smoke 09_00016","frameX":-30,"x":1924},{"frameY":-33,"y":1257,"frameWidth":300,"frameHeight":264,"width":222,"height":199,"name":"Smoke 09_00009","frameX":-38,"x":1899},{"frameY":-46,"y":1783,"frameWidth":300,"frameHeight":264,"width":192,"height":175,"name":"Smoke 09_00006","frameX":-54,"x":534},{"width":300,"y":1051,"height":264,"name":"Smoke 09_00017","x":1166},{"frameY":-27,"y":214,"frameWidth":300,"frameHeight":264,"width":240,"height":210,"name":"Smoke 09_00015","frameX":-30,"x":1924},{"frameY":-31,"y":1051,"frameWidth":300,"frameHeight":264,"width":231,"height":204,"name":"Smoke 09_00010","frameX":-34,"x":1704},{"frameY":-119,"y":1949,"frameWidth":300,"frameHeight":264,"width":22,"height":18,"name":"Smoke 09_00000","frameX":-144,"x":1056},{"frameY":-41,"y":1745,"frameWidth":300,"frameHeight":264,"width":201,"height":184,"name":"Smoke 09_00007","frameX":-48,"x":1283},{"frameY":-28,"y":1317,"frameWidth":300,"frameHeight":264,"width":238,"height":209,"name":"Smoke 09_00013","frameX":-31,"x":1420},{"frameY":-29,"y":1051,"frameWidth":300,"frameHeight":264,"width":234,"height":206,"name":"Smoke 09_00011","frameX":-32,"x":1468},{"frameY":-109,"y":1257,"frameWidth":300,"frameHeight":264,"width":47,"height":38,"name":"Smoke 09_00001","frameX":-132,"x":1850},{"frameY":-36,"y":1458,"frameWidth":300,"frameHeight":264,"width":213,"height":194,"name":"Smoke 09_00008","frameX":-42,"x":1899}],"height":2048}